README.rst
setup.py
django_rest_tzolkin.egg-info/PKG-INFO
django_rest_tzolkin.egg-info/SOURCES.txt
django_rest_tzolkin.egg-info/dependency_links.txt
django_rest_tzolkin.egg-info/requires.txt
django_rest_tzolkin.egg-info/top_level.txt
test_tzolkin/__init__.py
test_tzolkin/settings.py
test_tzolkin/urls.py
tzolkin/__init__.py
tzolkin/models.py
tzolkin/tests.py
tzolkin/urls.py
tzolkin/views.py
tzolkin/libs/__init__.py
tzolkin/libs/gregorian2tzolkin/__init__.py
tzolkin/libs/haab/__init__.py
tzolkin/libs/tzolkin/__init__.py
tzolkin/libs/tzolkin2gregorian/__init__.py
tzolkin/processor/__init__.py
tzolkin/serializers/__init__.py
tzolkin/subviews/__init__.py
tzolkin/subviews/gregorian2tzolkin/__init__.py
tzolkin/subviews/tzolkin2gregorian/__init__.py