Metadata-Version: 1.1
Name: django-rest-tzolkin
Version: 0.1
Summary: Django-Rest API for convert: Gregorian, Long Count, Haab and Tzolkin dates
Home-page: http://github.com/dimddev/django-rest-tzolkin
Author: Dim Mitar Hakini
Author-email: dmhakini@gmail.com
License: BSD
Platform: UNKNOWN
Classifier: Development Status :: 4 - Beta
Classifier: Environment :: Web Environment
Classifier: Framework :: Django
Classifier: Intended Audience :: Developers
Classifier: License :: OSI Approved :: GNU General Public License (GPL)
Classifier: Operating System :: OS Independent
Classifier: Programming Language :: Python
Classifier: Topic :: Internet :: WWW/HTTP
